twofas/__about__.py
twofas/__init__.py
twofas/cli.py
twofas/cli_settings.py
twofas/cli_support.py
twofas/py.typed
2fas-1.1.1.dist-info/METADATA
2fas-1.1.1.dist-info/WHEEL
2fas-1.1.1.dist-info/entry_points.txt
2fas-1.1.1.dist-info/licenses/LICENSE
2fas-1.1.1.dist-info/RECORD
